logctx/__init__.py
logctx/_core.py
logctx/decorators.py
logctx/py.typed
logctx-1.0.0.dist-info/licenses/LICENSE
logctx-1.0.0.dist-info/METADATA
logctx-1.0.0.dist-info/WHEEL
logctx-1.0.0.dist-info/top_level.txt
logctx-1.0.0.dist-info/RECORD
