Metadata-Version: 2.4
Name: logctx
Version: 1.0.0
Summary: Management and injection of contextual variables into log messages.
Author: Alexander Schulte
License-Expression: MIT
Project-URL: Homepage, https://github.com/aschulte201/logctx
Project-URL: Source, https://github.com/aschulte201/logctx
Project-URL: Documentation, https://github.com/aschulte201/logctx/blob/README.md
Project-URL: Changelog, https://github.com/aschulte201/logctx/blob/CHANGELOG.md
Keywords: logging,context,log,logger,logctx,log-context
Classifier: Development Status :: 4 - Beta
Classifier: Intended Audience :: Developers
Classifier: Natural Language :: English
Classifier: Operating System :: OS Independent
Classifier: Programming Language :: Python :: 3.9
Classifier: Programming Language :: Python :: 3.10
Classifier: Programming Language :: Python :: 3.11
Classifier: Programming Language :: Python :: 3.12
Classifier: Programming Language :: Python :: 3.13
Classifier: Programming Language :: Python :: Implementation :: CPython
Classifier: Topic :: Software Development :: Libraries :: Python Modules
Classifier: Typing :: Typed
Requires-Python: >=3.9
License-File: LICENSE
Requires-Dist: typing-extensions>=4.12
Dynamic: license-file
